hatch_rest_api/__init__.py
hatch_rest_api/aws_http.py
hatch_rest_api/callbacks.py
hatch_rest_api/const.py
hatch_rest_api/contentful.py
hatch_rest_api/errors.py
hatch_rest_api/hatch.py
hatch_rest_api/rest_baby.py
hatch_rest_api/rest_iot.py
hatch_rest_api/rest_mini.py
hatch_rest_api/rest_plus.py
hatch_rest_api/restore_iot.py
hatch_rest_api/restore_v4.py
hatch_rest_api/restore_v5.py
hatch_rest_api/shadow_client_subscriber.py
hatch_rest_api/stub.py
hatch_rest_api/types.py
hatch_rest_api/util.py
hatch_rest_api/util_bootstrap.py
hatch_rest_api/util_http.py
hatch_rest_api-1.32.0.dist-info/licenses/LICENSE
hatch_rest_api-1.32.0.dist-info/METADATA
hatch_rest_api-1.32.0.dist-info/WHEEL
hatch_rest_api-1.32.0.dist-info/top_level.txt
hatch_rest_api-1.32.0.dist-info/RECORD
