Metadata-Version: 2.4
Name: hatch_rest_api
Version: 1.32.0
Summary: Hatch Rest mini Api Wrapper
Author-email: Brendan Dahl <dahl.brendan@gmail.com>
Project-URL: Homepage, https://github.com/dahlb/hatch_rest_api
Project-URL: Bug Tracker, https://github.com/dahlb/hatch_rest_api/issues
Keywords: hatch,rest-mini,api
Classifier: Development Status :: 4 - Beta
Classifier: License :: OSI Approved :: MIT License
Classifier: Natural Language :: English
Classifier: Intended Audience :: Developers
Classifier: Programming Language :: Python :: 3.12
Classifier: Operating System :: MacOS :: MacOS X
Requires-Python: <4,>=3.12.0
License-File: LICENSE
Requires-Dist: aiohttp>=3.8.1
Requires-Dist: awsiotsdk>=1.16.0
Dynamic: license-file
